[
	
	//dmobs
	
	{
		"dimension": 10,
		"mob": "dungeonmobs:dmghoul",
		"random": 0.05,
		"maxlight": 15,
		"minlight": 0,
		"maxcount":	{
			"amount": 20,
			"perchunk": true
		},
		"result": "allow"
	},
	{
		"dimension": 10,
		"mob": "dungeonmobs:dmghoul",
		"result": "deny"
	},
	
	{
		"dimension": 10,
		"mob": "dungeonmobs:dmbeholder",
		"random": 0.0375,
		"maxlight": 7,
		"minlight": 0,
		"maxheight": 240,
		"minheight": 50,
		"maxcount":	{
			"amount": 4,
			"perchunk": true
		},
		"result": "allow"
	},
	{
		"dimension": 10,
		"mob": "dungeonmobs:dmbeholder",
		"result": "deny"
	},
	
	{
		"dimension": 10,
		"mob": "dungeonmobs:dmtroll",
		"random": 0.0125,
		"maxcount":	{
			"amount": 4,
			"perchunk": true
		},
		"result": "allow"
	},
	{
		"dimension": 10,
		"mob": "dungeonmobs:dmtroll",
		"result": "deny"
	},
	
	{
		"dimension": 10,
		"mob": "dungeonmobs:dmumberhulk",
		"random": 0.0125,
		"maxcount":	{
			"amount": 4,
			"perchunk": true
		},
		"result": "allow"
	},
	{
		"dimension": 10,
		"mob": "dungeonmobs:dmumberhulk",
		"result": "deny"
	},

	//techguns

	{
		"dimension": 0,
		"mob": "techguns:zombiesoldier",
		"random": 0.0025,
		"gamestage": "tg",
		"maxlight": 7,
		"minlight": 0,
		"maxcount":	{
			"amount": 10,
			"perchunk": true
		},
		"result": "allow"
	},
	{
		"dimension": 10,
		"mob": "techguns:zombiesoldier",
		"random": 0.0375,
		"maxlight": 7,
		"minlight": 0,
		"maxheight": 128,
		"maxcount":	{
			"amount": 15,
			"perchunk": true
		},
		"result": "allow"
	},
	{
		"dimension": [0,10],
		"mob": "techguns:zombiesoldier",
		"result": "deny"
	},

	{
		"dimension": 0,
		"mob": "techguns:zombiefarmer",
		"random": 0.00375,
		"gamestage": "tg",
		"maxlight": 7,
		"minlight": 0,
		"maxcount":	{
			"amount": 15,
			"perchunk": true
		},
		"result": "allow"
	},
	{
		"dimension": 10,
		"mob": "techguns:zombiefarmer",
		"random": 0.025,
		"maxlight": 7,
		"minlight": 0,
		"maxcount":	{
			"amount": 10,
			"perchunk": true
		},
		"result": "allow"
	},
	{
		"dimension": [0,10],
		"mob": "techguns:zombiefarmer",
		"result": "deny"
	},

	{
		"dimension": 0,
		"mob": "techguns:zombieminer",
		"random": 0.00375,
		"gamestage": "tg",
		"maxlight": 7,
		"minlight": 0,
		"maxcount":	{
			"amount": 15,
			"perchunk": true
		},
		"result": "allow"
	},
	{
		"dimension": 10,
		"mob": "techguns:zombieminer",
		"random": 0.05,
		"maxlight": 7,
		"minlight": 0,
		"maxcount":	{
			"amount": 20,
			"perchunk": true
		},
		"result": "allow"
	},
	{
		"dimension": [0,10],
		"mob": "techguns:zombieminer",
		"result": "deny"
	},

	{
		"dimension": -1,
		"mob": "techguns:cyberdemon",
		"random": 0.00125,
		"maxcount":	{
			"amount": 4,
			"perchunk": true
		},
		"result": "allow"
	},
	{
		"dimension": -1,
		"mob": "techguns:cyberdemon",
		"result": "deny"
	},

	{
		"dimension": 0,
		"mob": "techguns:skeletonsoldier",
		"random": 0.0025,
		"gamestage": "tg",
		"maxlight": 7,
		"minlight": 0,
		"maxcount":	{
			"amount": 10,
			"perchunk": true
		},
		"result": "allow"
	},
	{
		"dimension": 10,
		"mob": "techguns:skeletonsoldier",
		"random": 0.0375,
		"maxlight": 7,
		"minlight": 0,
		"maxheight": 128,
		"maxcount":	{
			"amount": 15,
			"perchunk": true
		},
		"result": "allow"
	},
	{
		"dimension": [0,10],
		"mob": "techguns:skeletonsoldier",
		"result": "deny"
	},

	{
		"dimension": 0,
		"mob": "techguns:psychosteve",
		"random": 0.000875,
		"gamestage": "tg",
		"maxlight": 7,
		"minlight": 0,
		"maxcount":	{
			"amount": 2,
			"perplayer": true
		},
		"result": "allow"
	},
	{
		"dimension": 10,
		"mob": "techguns:psychosteve",
		"random": 0.0125,
		"maxlight": 7,
		"minlight": 0,
		"maxcount":	{
			"amount": 2,
			"perplayer": true
		},
		"result": "allow"
	},
	{
		"dimension": [0,10],
		"mob": "techguns:psychosteve",
		"result": "deny"
	},

	{
		"dimension": 10,
		"mob": "techguns:supermutantbasic",
		"random": 0.025,
		"maxlight": 7,
		"minlight": 0,
		"maxheight": 96,
		"maxcount":	{
			"amount": 4,
			"perchunk": true
		},
		"result": "allow"
	},
	{
		"dimension": 10,
		"mob": "techguns:supermutantbasic",
		"result": "deny"
	},

	{
		"dimension": 10,
		"mob": "techguns:supermutantheavy",
		"random": 0.0125,
		"maxlight": 7,
		"minlight": 0,
		"maxheight": 96,
		"maxcount":	{
			"amount": 2,
			"perchunk": true
		},
		"result": "allow"
	},
	{
		"dimension": 10,
		"mob": "techguns:supermutantheavy",
		"result": "deny"
	},

	{
		"dimension": 10,
		"mob": "techguns:supermutantelite",
		"random": 0.00875,
		"maxlight": 7,
		"minlight": 0,
		"maxheight": 96,
		"maxcount":	{
			"amount": 2,
			"perchunk": true
		},
		"result": "allow"
	},
	{
		"dimension": 10,
		"mob": "techguns:supermutantelite",
		"result": "deny"
	},

	{
		"dimension": 1,
		"mob": "techguns:stormtrooper",
		"random": 0.000625,
		"maxlight": 7,
		"minlight": 0,
		"maxcount":	{
			"amount": 16,
			"perchunk": true
		},
		"result": "allow"
	},
	{
		"dimension": 1,
		"mob": "techguns:stormtrooper",
		"result": "deny"
	},

	//ice&fire dreads
	
	{
		"dimension": 0,
		"mob": "iceandfire:dread_thrall",
		"random": 0.0025,
		"seesky": true,
		"maxlight": 7,
		"minlight": 0,
		"minheight": 50,
		"winter": true,
		"maxcount":	{
			"amount": 20,
			"perchunk": true
		},
		"result": "allow"
	},
	{
		"dimension": 0,
		"mob": "iceandfire:dread_thrall",
		"result": "deny"
	},
	
	{
		"dimension": 0,
		"mob": "iceandfire:dread_ghoul",
		"random": 0.00125,
		"seesky": true,
		"maxlight": 7,
		"minlight": 0,
		"minheight": 50,
		"winter": true,
		"maxcount":	{
			"amount": 4,
			"perchunk": true
		},
		"result": "allow"
	},
	{
		"dimension": 0,
		"mob": "iceandfire:dread_ghoul",
		"result": "deny"
	},
	
	{
		"dimension": 0,
		"mob": "iceandfire:dread_beast",
		"random": 0.00125,
		"seesky": true,
		"maxlight": 7,
		"minlight": 0,
		"minheight": 50,
		"winter": true,
		"maxcount":	{
			"amount": 4,
			"perchunk": true
		},
		"result": "allow"
	},
	{
		"dimension": 0,
		"mob": "iceandfire:dread_beast",
		"result": "deny"
	},
	
	{
		"dimension": 0,
		"mob": "iceandfire:dread_scuttler",
		"random": 0.000875,
		"seesky": true,
		"maxlight": 7,
		"minlight": 0,
		"minheight": 50,
		"winter": true,
		"maxcount":	{
			"amount": 3,
			"perchunk": true
		},
		"result": "allow"
	},
	{
		"dimension": 0,
		"mob": "iceandfire:dread_scuttler",
		"result": "deny"
	},
	
	{
		"dimension": 0,
		"mob": "iceandfire:dread_lich",
		"random": 0.000625,
		"seesky": true,
		"maxlight": 7,
		"minlight": 0,
		"minheight": 50,
		"winter": true,
		"maxcount":	{
			"amount": 2,
			"perchunk": true
		},
		"result": "allow"
	},
	{
		"dimension": 0,
		"mob": "iceandfire:dread_lich",
		"result": "deny"
	},
	
	{
		"dimension": 0,
		"mob": "iceandfire:dread_knight",
		"random": 0.00125,
		"seesky": true,
		"maxlight": 7,
		"minlight": 0,
		"minheight": 50,
		"winter": true,
		"maxcount":	{
			"amount": 3,
			"perchunk": true
		},
		"result": "allow"
	},
	{
		"dimension": 0,
		"mob": "iceandfire:dread_knight",
		"result": "deny"
	},
	
	//GoG

	{
		"dimension": 0,
		"mob": "grimoireofgaia:deathword",
		"random": 0.0025,
		"seesky": false,
		"maxlight": 7,
		"minlight": 0,
		"maxcount": {
			"amount": 3,
			"perchunk": true
		},
		"result": "allow"
	},
	{
		"dimension": 0,
		"mob": "grimoireofgaia:deathword",
		"result": "deny"
	},
	
	{
		"dimension": 0,
		"mob": "grimoireofgaia:dhampir",
		"random": 0.00125,
		"seesky": true,
		"biometype": ["CONIFEROUS", "DENSE", "THEMED_TREES", "SPOOKY", "MEGA_TAIGA_TREES", "MEGA_TAIGA_SPRUCE_TREES", "MAGICAL", "DEAD"],
		"maxlight": 15,
		"minlight": 0,
		"maxcount":	{
			"amount": 2,
			"perchunk": true
		},
		"result": "allow"
	},
	{
		"dimension": 0,
		"mob": "grimoireofgaia:dhampir",
		"result": "deny"
	},

	{
		"dimension": 0,
		"mob": "grimoireofgaia:vampire",
		"random": 0.000875,
		"seesky": true,
		"biometype": ["CONIFEROUS", "DENSE", "THEMED_TREES", "SPOOKY", "MEGA_TAIGA_TREES", "MEGA_TAIGA_SPRUCE_TREES", "MAGICAL", "DEAD"],
		"maxlight": 7,
		"minlight": 0,
		"maxcount":	{
			"amount": 2,
			"perchunk": true
		},
		"result": "allow"
	},
	{
		"dimension": 0,
		"mob": "grimoireofgaia:vampire",
		"result": "deny"
	},

	{
		"dimension": 0,
		"mob": "grimoireofgaia:dwarf",
		"random": 0.0025,
		"seesky": false,
		"maxlight": 7,
		"minlight": 0,
		"maxheight": 64,
		"minheight": 4,
		"maxcount": {
			"amount": 9,
			"perchunk": true
		},
		"result": "allow"
	},
	{
		"dimension": 0,
		"mob": "grimoireofgaia:dwarf",
		"result": "deny"
	},

	{
		"dimension": 0,
		"mob": "grimoireofgaia:orc",
		"random": 0.0025,
		"seesky": false,
		"maxlight": 7,
		"minlight": 0,
		"maxheight": 64,
		"minheight": 4,
		"maxcount": {
			"amount": 9,
			"perchunk": true
		},
		"result": "allow"
	},
	{
		"dimension": 0,
		"mob": "grimoireofgaia:orc",
		"result": "deny"
	},
	
	//eyes
	
	{
		"dimension": [0,3,5,424],
		"mob": "eyesinthedarkness:eyes",
		"random": 0.00625,
		"seesky": false,
		"maxlight": 7,
		"minlight": 0,
		"maxcount":	{
			"amount": 6,
			"perplayer": true
		},
		"result": "allow"
	},
	{
		"dimension": [0,3,5,424],
		"mob": "eyesinthedarkness:eyes",
		"result": "deny"
	},

	//srpbeckonsskycheck

	{
		"dimension": 0,
		"mob": ["srparasites:beckon_si","srparasites:beckon_sii","srparasites:beckon_siii","srparasites:beckon_siv"],
		"onjoin": true,
		"seesky": false,
		"result": "deny"
	},

	//roughmobsbossesskycheck
	
	{
		"dimension": 0,
		"mob": ["roughmobsrevamped:bosszombie","roughmobsrevamped:bossskeleton"],
		"onjoin": true,
		"seesky": false,
		"result": "deny"
	},
	
	//roughmobsbossesbeneathdespawn

	{
		"dimension": [3,5,7,10],
		"mob": ["roughmobsrevamped:bosszombie","roughmobsrevamped:bossskeleton"],
		"onjoin": true,
		"result": "deny"
	},

	//beneath

	{
		"dimension": 10,
		"mob": ["beneath:shadow","beneath:hand","charm:spectre"],
		"result": "deny"
	},

	//srp

	{
		"dimension": 10,
		"mob": "srparasites:warden",
		"random": 0.00375,
		"gamestage": "ob",
		"maxlight": 7,
		"minlight": 0,
		"maxheight": 32,
		"maxcount":	{
			"amount": 2,
			"perchunk": true
		},
		"result": "allow"
	},
	{
		"dimension": 10,
		"mob": "srparasites:warden",
		"result": "deny"
	},

	{
		"dimension": 10,
		"mob": "srparasites:marauder",
		"random": 0.0025,
		"gamestage": "ob",
		"maxlight": 7,
		"minlight": 0,
		"maxheight": 32,
		"maxcount":	{
			"amount": 2,
			"perchunk": true
		},
		"result": "allow"
	},
	{
		"dimension": 10,
		"mob": "srparasites:marauder",
		"result": "deny"
	},

	{
		"dimension": 10,
		"mob": "srparasites:overseer",
		"random": 0.00125,
		"gamestage": "ob",
		"maxlight": 7,
		"minlight": 0,
		"maxheight": 64,
		"maxcount":	{
			"amount": 2,
			"perchunk": true
		},
		"result": "allow"
	},
	{
		"dimension": 10,
		"mob": "srparasites:overseer",
		"result": "deny"
	},

	{
		"dimension": 10,
		"mob": "srparasites:bomber_light",
		"random": 0.00125,
		"gamestage": "ob",
		"maxlight": 7,
		"minlight": 0,
		"maxheight": 64,
		"maxcount":	{
			"amount": 2,
			"perchunk": true
		},
		"result": "allow"
	},
	{
		"dimension": 10,
		"mob": "srparasites:bomber_light",
		"result": "deny"
	},

	{
		"dimension": 10,
		"mob": "srparasites:monarch",
		"random": 0.00375,
		"gamestage": "ob",
		"maxlight": 7,
		"minlight": 0,
		"maxheight": 48,
		"maxcount":	{
			"amount": 2,
			"perchunk": true
		},
		"result": "allow"
	},
	{
		"dimension": 10,
		"mob": "srparasites:monarch",
		"result": "deny"
	},
	
	{
		"dimension": 10,
		"mob": ["srparasites:pri_longarms","srparasites:pri_manducater","srparasites:pri_reeker","srparasites:pri_summoner","srparasites:pri_bolster","srparasites:pri_arachnida"],
		"random": 0.005,
		"gamestage": "ob",
		"maxlight": 7,
		"minlight": 0,
		"maxheight": 64,
		"maxcount":	{
			"amount": 6,
			"perchunk": true
		},
		"result": "allow"
	},
	{
		"dimension": 10,
		"mob": ["srparasites:pri_longarms","srparasites:pri_manducater","srparasites:pri_reeker","srparasites:pri_summoner","srparasites:pri_bolster","srparasites:pri_arachnida"],
		"result": "deny"
	},

	{
		"dimension": 0,
		"mob": "srparasites:carrier_heavy",
		"random": 0.001,
		"gamestage": "ob",
		"maxlight": 7,
		"minlight": 0,
		"maxcount":	{
			"amount": 4,
			"perchunk": true
		},
		"result": "allow"
	},
	{
		"dimension": 10,
		"mob": "srparasites:carrier_heavy",
		"random": 0.01,
		"gamestage": "ob",
		"maxlight": 7,
		"minlight": 0,
		"maxheight": 96,
		"maxcount":	{
			"amount": 4,
			"perchunk": true
		},
		"result": "allow"
	},
	{
		"dimension": [0,10],
		"mob": "srparasites:carrier_heavy",
		"result": "deny"
	},

	{
		"dimension": 10,
		"mob": "srparasites:carrier_flying",
		"random": 0.0375,
		"gamestage": "ob",
		"maxlight": 7,
		"minlight": 0,
		"maxheight": 128,
		"minheight": 64,
		"maxcount":	{
			"amount": 3,
			"perchunk": true
		},
		"result": "allow"
	},
	{
		"dimension": 10,
		"mob": "srparasites:carrier_flying",
		"result": "deny"
	},

	{
		"dimension": 0,
		"mob": "srparasites:rupter",
		"random": 0.001,
		"gamestage": "ob",
		"maxlight": 7,
		"minlight": 0,
		"maxcount":	{
			"amount": 30,
			"perchunk": true
		},
		"result": "allow"
	},
	{
		"dimension": 10,
		"mob": "srparasites:rupter",
		"random": 0.1,
		"gamestage": "ob",
		"maxlight": 7,
		"minlight": 0,
		"maxheight": 96,
		"maxcount":	{
			"amount": 30,
			"perchunk": true
		},
		"result": "allow"
	},
	{
		"dimension": [0,10],
		"mob": "srparasites:rupter",
		"result": "deny"
	},

	{
		"dimension": 0,
		"mob": "srparasites:sim_human",
		"random": 0.001,
		"gamestage": "ob",
		"maxlight": 7,
		"minlight": 0,
		"maxcount":	{
			"amount": 15,
			"perchunk": true
		},
		"result": "allow"
	},
	{
		"dimension": 10,
		"mob": "srparasites:sim_human",
		"random": 0.05,
		"gamestage": "ob",
		"maxlight": 7,
		"minlight": 0,
		"maxheight": 96,
		"maxcount":	{
			"amount": 15,
			"perchunk": true
		},
		"result": "allow"
	},
	{
		"dimension": [0,10],
		"mob": "srparasites:sim_human",
		"result": "deny"
	},

	//nco

	{
		"dimension": 0,
		"mob": "nuclearcraft:feral_ghoul",
		"random": 0.0025,
		"gamestage": "nco",
		"maxlight": 7,
		"minlight": 0,
		"maxcount":	{
			"amount": 15,
			"perchunk": true
		},
		"result": "allow"
	},
	{
		"dimension": 10,
		"mob": "nuclearcraft:feral_ghoul",
		"random": 0.05,
		"maxlight": 7,
		"minlight": 0,
		"maxheight": 192,
		"maxcount":	{
			"amount": 15,
			"perchunk": true
		},
		"result": "allow"
	},
	{
		"dimension": [0,10],
		"mob": "nuclearcraft:feral_ghoul",
		"result": "deny"
	},

	//revs

	{
		"dimension": 0,
		"mob": ["srrevenants:for_bear","srrevenants:for_cow","srrevenants:for_horse","srrevenants:for_human","srrevenants:for_pig","srrevenants:for_sheep"],
		"random": 0.05,
		"maxlight": 7,
		"minlight": 0,
		"maxspawndist": 128,
		"maxcount":	{
			"amount": 6,
			"perchunk": true
		},
		"result": "allow"
	},
	{
		"dimension": 0,
		"mob": ["srrevenants:for_bear","srrevenants:for_cow","srrevenants:for_horse","srrevenants:for_human","srrevenants:for_pig","srrevenants:for_sheep"],
		"result": "deny"
	},

	//lm

	{
		"dimension": [3,5,7],
		"mob": ["lycanitesmobs:ghoul","lycanitesmobs:kobold","lycanitesmobs:wraamon","lycanitesmobs:aglebemu","lycanitesmobs:darkling"],
		"random": 0.05,
		"maxlight": 7,
		"minlight": 0,
		"maxheight": 192,
		"maxcount":	{
			"amount": 10,
			"perchunk": true
		},
		"result": "allow"
	},
	{
		"dimension": [3,5,7],
		"mob": ["lycanitesmobs:ghoul","lycanitesmobs:kobold","lycanitesmobs:wraamon","lycanitesmobs:aglebemu","lycanitesmobs:darkling"],
		"result": "deny"
	},
	//abyss
	{
		"dimension": 3,
		"mob": ["lycanitesmobs:remobra","lycanitesmobs:aspid","lycanitesmobs:calpod","lycanitesmobs:eyewig","lycanitesmobs:lurker","lycanitesmobs:gorgomite"],
		"random": 0.05,
		"maxlight": 7,
		"minlight": 0,
		"maxheight": 192,
		"maxcount":	{
			"amount": 10,
			"perchunk": true
		},
		"result": "allow"
	},
	{
		"dimension": 3,
		"mob": ["lycanitesmobs:remobra","lycanitesmobs:aspid","lycanitesmobs:calpod","lycanitesmobs:eyewig","lycanitesmobs:lurker","lycanitesmobs:gorgomite"],
		"result": "deny"
	},
	//under
	{
		"dimension": 5,
		"mob": ["lycanitesmobs:necrovore","lycanitesmobs:gnekk","lycanitesmobs:cacodemon","lycanitesmobs:astaroth","lycanitesmobs:trite","lycanitesmobs:vorach"],
		"random": 0.05,
		"maxlight": 7,
		"minlight": 0,
		"maxheight": 192,
		"maxcount":	{
			"amount": 10,
			"perchunk": true
		},
		"result": "allow"
	},
	{
		"dimension": 5,
		"mob": ["lycanitesmobs:necrovore","lycanitesmobs:gnekk","lycanitesmobs:cacodemon","lycanitesmobs:astaroth","lycanitesmobs:trite","lycanitesmobs:vorach"],
		"result": "deny"
	},
	//chasm
	{
		"dimension": 7,
		"mob": "lycanitesmobs:dweller",
		"random": 0.05,
		"maxlight": 7,
		"minlight": 0,
		"maxheight": 184,
		"maxcount":	{
			"amount": 10,
			"perchunk": true
		},
		"result": "allow"
	},
	{
		"dimension": 7,
		"mob": "lycanitesmobs:dweller",
		"result": "deny"
	},

	//theaurorian

	{
		"dimension": 3,
		"mob": ["theaurorian:disturbedhollow","theaurorian:spirit"],
		"random": 0.05,
		"maxlight": 7,
		"minlight": 0,
		"maxheight": 192,
		"maxcount":	{
			"amount": 5,
			"perchunk": true
		},
		"result": "allow"
	},
	{
		"dimension": 3,
		"mob": ["theaurorian:disturbedhollow","theaurorian:spirit"],
		"result": "deny"
	},

	//fishundeadmobcounter

	{
		"mob": "mod_lavacow:raven",
		"mincount": {
			"amount": 15,
			"mob": "mod_lavacow:raven",
			"perchunk": true
		},
		"result": "deny"
	},
	{
		"mob": "mod_lavacow:mimic",
		"mincount": {
			"amount": 10,
			"mob": "mod_lavacow:mimic",
			"perchunk": true
		},
		"result": "deny"
	},
	{
		"mob": "mod_lavacow:piranha",
		"mincount": {
			"amount": 15,
			"mob": "mod_lavacow:piranha",
			"perchunk": true
		},
		"result": "deny"
	},
	{
		"mob": "mod_lavacow:zombiepiranha",
		"mincount": {
			"amount": 15,
			"mob": "mod_lavacow:zombiepiranha",
			"perchunk": true
		},
		"result": "deny"
	},
	{
		"mob": "mod_lavacow:weta",
		"mincount": {
			"amount": 15,
			"mob": "mod_lavacow:weta",
			"perchunk": true
		},
		"result": "deny"
	},
	{
		"mob": "mod_lavacow:banshee",
		"mincount": {
			"amount": 5,
			"mob": "mod_lavacow:banshee",
			"perchunk": true
		},
		"result": "deny"
	},
	{
		"mob": "mod_lavacow:ghostray",
		"mincount": {
			"amount": 5,
			"mob": "mod_lavacow:ghostray",
			"perchunk": true
		},
		"result": "deny"
	},
	{
		"mob": "mod_lavacow:enigmoth",
		"mincount": {
			"amount": 1,
			"mob": "mod_lavacow:enigmoth",
			"perchunk": true
		},
		"result": "deny"
	},
	{
		"mob": "mod_lavacow:enigmoth_larva",
		"mincount": {
			"amount": 1,
			"mob": "mod_lavacow:enigmoth_larva",
			"perchunk": true
		},
		"result": "deny"
	},

	//beecounter

	{
		"mob": "futuremc:bee",
		"mincount": {
			"amount": 15,
			"mob": "futuremc:bee",
			"perchunk": true
		},
		"result": "deny"
	},

	//gogcounter

	{
		"mob": "grimoireofgaia:chest",
		"mincount": {
			"amount": 15,
			"mob": "grimoireofgaia:chest",
			"perchunk": true
		},
		"result": "deny"
	},
	{
		"mob": "grimoireofgaia:mimic",
		"mincount": {
			"amount": 15,
			"mob": "grimoireofgaia:mimic",
			"perchunk": true
		},
		"result": "deny"
	},
	{
		"mob": "grimoireofgaia:arachne",
		"mincount": {
			"amount": 10,
			"mob": "grimoireofgaia:arachne",
			"perchunk": true
		},
		"result": "deny"
	},
	{
		"mob": "grimoireofgaia:centaur",
		"mincount": {
			"amount": 15,
			"mob": "grimoireofgaia:centaur",
			"perchunk": true
		},
		"result": "deny"
	},
	{
		"mob": "grimoireofgaia:creep",
		"mincount": {
			"amount": 10,
			"mob": "grimoireofgaia:creep",
			"perchunk": true
		},
		"result": "deny"
	},
	{
		"mob": "grimoireofgaia:cyan_flower",
		"mincount": {
			"amount": 15,
			"mob": "grimoireofgaia:cyan_flower",
			"perchunk": true
		},
		"result": "deny"
	},
	{
		"mob": "grimoireofgaia:ender_eye",
		"mincount": {
			"amount": 10,
			"mob": "grimoireofgaia:ender_eye",
			"perchunk": true
		},
		"result": "deny"
	},
	{
		"mob": "grimoireofgaia:satyress",
		"mincount": {
			"amount": 15,
			"mob": "grimoireofgaia:satyress",
			"perchunk": true
		},
		"result": "deny"
	},
	{
		"mob": "grimoireofgaia:vase",
		"mincount": {
			"amount": 15,
			"mob": "grimoireofgaia:vase",
			"perchunk": true
		},
		"result": "deny"
	},
	{
		"mob": "grimoireofgaia:vase_nether",
		"mincount": {
			"amount": 15,
			"mob": "grimoireofgaia:vase_nether",
			"perchunk": true
		},
		"result": "deny"
	},
	{
		"mob": "grimoireofgaia:ant_hill",
		"mincount": {
			"amount": 15,
			"mob": "grimoireofgaia:ant_hill",
			"perchunk": true
		},
		"result": "deny"
	},
	{
		"mob": "grimoireofgaia:ant_ranger",
		"mincount": {
			"amount": 15,
			"mob": "grimoireofgaia:ant_ranger",
			"perchunk": true
		},
		"result": "deny"
	},

	//mutantbeastscounter

	{
		"mob": "mutantbeasts:mutant_enderman",
		"mincount": {
			"amount": 3,
			"mob": "mutantbeasts:mutant_enderman",
			"perchunk": true
		},
		"result": "deny"
	},
	{
		"mob": "mutantbeasts:mutant_skeleton",
		"mincount": {
			"amount": 2,
			"mob": "mutantbeasts:mutant_skeleton",
			"perchunk": true
		},
		"result": "deny"
	},

	//chickenscounter

	{
		"mob": "chickens:chickenschicken",
		"mincount": {
			"amount": 3,
			"mob": "chickens:chickenschicken",
			"perchunk": true
		},
		"result": "deny"
	},

	//salmoncounter

	{
		"mob": "oe:salmon",
		"mincount": {
			"amount": 15,
			"mob": "oe:salmon",
			"perchunk": true
		},
		"result": "deny"
	},

	//quarkcounter

	{
		"mob": "quark:stoneling",
		"mincount": {
			"amount": 15,
			"mob": "quark:stoneling",
			"perchunk": true
		},
		"result": "deny"
	},

	//ebwcounter

	{
		"mob": "ancientspellcraft:wizardmerchant",
		"mincount": {
			"amount": 10,
			"mob": "ancientspellcraft:wizardmerchant",
			"perchunk": true
		},
		"result": "deny"
	},

	//vanillamobcounter

	{
		"mob": "minecraft:bat",
		"mincount": {
			"amount": 15,
			"mob": "minecraft:bat",
			"perchunk": true
		},
		"result": "deny"
	},
	{
		"mob": "minecraft:slime",
		"onjoin": true,
		"mincount": {
			"amount": 30,
			"mob": "minecraft:slime",
			"perchunk": true
		},
		"result": "deny"
	},
	{
		"mob": "minecraft:enderman",
		"mincount": {
			"amount": 6,
			"mob": "minecraft:enderman",
			"perchunk": true
		},
		"result": "deny"
	},
	{
		"mob": "minecraft:creeper",
		"mincount": {
			"amount": 12,
			"mob": "minecraft:creeper",
			"perchunk": true
		},
		"result": "deny"
	},
	{
		"mob": "minecraft:skeleton",
		"mincount": {
			"amount": 30,
			"mob": "minecraft:skeleton",
			"perchunk": true
		},
		"result": "deny"
	},
	{
		"mob": "minecraft:zombie",
		"mincount": {
			"amount": 60,
			"mob": "minecraft:zombie",
			"perchunk": true
		},
		"result": "deny"
	},

	//srphack

	{
		"mob": "srparasites:beckon_si",
		"onjoin": true,
		"mincount": {
			"amount": 9,
			"mob": "srparasites:beckon_si",
			"perchunk": true
		},
		"result": "deny"
	},
	{
		"mob": "srparasites:beckon_sii",
		"onjoin": true,
		"mincount": {
			"amount": 7,
			"mob": "srparasites:beckon_sii",
			"perchunk": true
		},
		"result": "deny"
	},
	{
		"mob": "srparasites:beckon_siii",
		"onjoin": true,
		"mincount": {
			"amount": 5,
			"mob": "srparasites:beckon_siii",
			"perchunk": true
		},
		"result": "deny"
	},
	{
		"mob": "srparasites:beckon_siv",
		"onjoin": true,
		"mincount": {
			"amount": 3,
			"mob": "srparasites:beckon_siv",
			"perchunk": true
		},
		"result": "deny"
	},
	{
		"mob": "srparasites:fer_enderman",
		"onjoin": true,
		"mincount": {
			"amount": 9,
			"mob": "srparasites:fer_enderman",
			"perchunk": true
		},
		"result": "deny"
	},
	{
		"mob": "srparasites:sim_enderman",
		"onjoin": true,
		"mincount": {
			"amount": 9,
			"mob": "srparasites:sim_enderman",
			"perchunk": true
		},
		"result": "deny"
	},
	{
		"mob": ["srparasites:dispatcher_si","srparasites:dispatcher_sii","srparasites:dispatcher_siii","srparasites:dispatcher_siv"],
		"onjoin": true,
		"result": "deny"
	},

	{
		"mob": "cqrepoured:nether_dragon",
		"onjoin": true,
		"result": "deny"
	}
]